MANIFEST.in
README.rst
setup.py
pywinExcel.egg-info/PKG-INFO
pywinExcel.egg-info/SOURCES.txt
pywinExcel.egg-info/dependency_links.txt
pywinExcel.egg-info/not-zip-safe
pywinExcel.egg-info/top_level.txt
pywinexcel/__init__.py
pywinexcel/pyExcel.py