Metadata-Version: 1.1
Name: pywinExcel
Version: 0.1.1
Summary: Python API to Excel 
Home-page: https://github.com/spidezad/pywinexcel
Author: Tan Kok Hua
Author-email: kokhua81@gmail.com
License: UNKNOWN
Keywords: python windows MsExcel Excel
Platform: UNKNOWN
Classifier: Development Status :: 3 - Alpha
Classifier: Operating System :: Microsoft :: Windows
Classifier: Environment :: Win32 (MS Windows)
Classifier: Programming Language :: Python :: 2.7
Classifier: Topic :: Software Development :: Libraries :: Python Modules
